odoo/addons/__init__.py
odoo/addons/l10n_fr_certification/__init__.py
odoo/addons/l10n_fr_certification/__manifest__.py
odoo/addons/l10n_fr_certification/data/account_move.xml
odoo/addons/l10n_fr_certification/models/__init__.py
odoo/addons/l10n_fr_certification/models/account.py
odoo/addons/l10n_fr_certification/models/res_company.py
odoo/addons/l10n_fr_certification/views/no_cancel.xml
odooku_odoo_l10n_fr_certification-10.0.0.dist-info/DESCRIPTION.rst
odooku_odoo_l10n_fr_certification-10.0.0.dist-info/METADATA
odooku_odoo_l10n_fr_certification-10.0.0.dist-info/RECORD
odooku_odoo_l10n_fr_certification-10.0.0.dist-info/WHEEL
odooku_odoo_l10n_fr_certification-10.0.0.dist-info/metadata.json
odooku_odoo_l10n_fr_certification-10.0.0.dist-info/top_level.txt
